pi_gcs/__init__.py
pi_gcs/__version__.py
pi_gcs/abstract_gcs2.py
pi_gcs/abstract_tip_tilt_2_axes.py
pi_gcs/data_recorder_configuration.py
pi_gcs/decorator.py
pi_gcs/fake_gcs2.py
pi_gcs/fake_tip_tilt_2_axis.py
pi_gcs/gcs2.py
pi_gcs/pi_e518.py
pi_gcs/tip_tilt_2_axes.py
pi_gcs/tip_tilt_configuration.py
pi_gcs-0.7.0.dist-info/DESCRIPTION.rst
pi_gcs-0.7.0.dist-info/METADATA
pi_gcs-0.7.0.dist-info/RECORD
pi_gcs-0.7.0.dist-info/WHEEL
pi_gcs-0.7.0.dist-info/metadata.json
pi_gcs-0.7.0.dist-info/top_level.txt
