Metadata-Version: 2.0
Name: pi-gcs
Version: 0.7.0
Summary: Unofficial python wrapper for Physik Instrumente General Command Set API
Home-page: https://github.com/lbusoni/pi_gcs
Author: Lorenzo Busoni
Author-email: lorenzo.busoni@inaf.it
License: MIT
Keywords: PI, GCS2, GCS, plico, Physik Instrument, piezo, laboratory, instrumentation control
Platform: UNKNOWN
Classifier: Development Status :: 4 - Beta
Classifier: Operating System :: POSIX :: Linux
Classifier: Intended Audience :: Developers
Classifier: Topic :: Software Development :: Build Tools
Classifier: Programming Language :: Python :: 3.5
Classifier: Programming Language :: Python :: 3.6
